Metadata-Version: 2.4
Name: lightwheel_sdk
Version: 0.25
Requires-Dist: requests
Requires-Dist: tqdm
Requires-Dist: termcolor
Requires-Dist: pyyaml
Requires-Dist: click
Provides-Extra: test
Requires-Dist: pytest>=7.0.0; extra == "test"
Requires-Dist: pytest-cov>=4.0.0; extra == "test"
Requires-Dist: pytest-mock>=3.10.0; extra == "test"
